[
  {
    "name": "Gnaeus Pompeius ",
    "image": "/paladin.jpg",
    "class": "Paladin"
  },
  {
    "name": "Gaius Julius Caesar",
    "image": "/paladin.jpg",
    "class": "Wizard"
  },
  {
    "name": "Pedro",
    "image": "/paladin.jpg",
    "class": "Paladin"
  },
  {
    "name": "Papito",
    "image": "/paladin.jpg",
    "class": "Paladin"
  },
  {
    "name": "Papitx",
    "image": "/paladin.jpg",
    "class": "Paladin"
  },
  {
    "name": "Papita",
    "image": "/paladin.jpg",
    "class": "Paladin"
  },
  {
    "name": "Papite",
    "image": "/paladin.jpg",
    "class": "Paladin"
  },
  {
    "name": "Papiti",
    "image": "/paladin.jpg",
    "class": "Paladin"
  },
  {
    "name": "Papitu",
    "image": "/paladin.jpg",
    "class": "Paladin"
  }
]